intake_oceantide/__init__.py
intake_oceantide/intake_oceantide.py
intake_oceantide/source.py
intake_oceantide/utils.py
intake_oceantide-0.1.0.dist-info/licenses/AUTHORS.rst
intake_oceantide-0.1.0.dist-info/licenses/LICENSE
intake_oceantide-0.1.0.dist-info/METADATA
intake_oceantide-0.1.0.dist-info/WHEEL
intake_oceantide-0.1.0.dist-info/entry_points.txt
intake_oceantide-0.1.0.dist-info/top_level.txt
intake_oceantide-0.1.0.dist-info/RECORD
