Metadata-Version: 2.4
Name: intake_oceantide
Version: 0.1.0
Summary: Intake driver for oceantide
Author-email: Oceanum Developers <developers@oceanum.science>
Maintainer-email: Oceanum Developers <developers@oceanum.science>
License: MIT license
Project-URL: bugs, https://github.com/oceanum/intake_oceantide/issues
Project-URL: changelog, https://github.com/oceanum/intake_oceantide/blob/master/changelog.md
Project-URL: homepage, https://github.com/oceanum/intake_oceantide
License-File: LICENSE
License-File: AUTHORS.rst
Requires-Dist: fsspec
Requires-Dist: intake
Requires-Dist: numpy
Requires-Dist: oceantide
Requires-Dist: pandas
Requires-Dist: typer
Requires-Dist: xarray
Requires-Dist: zarr
Provides-Extra: dev
Requires-Dist: coverage; extra == "dev"
Requires-Dist: ipdb; extra == "dev"
Requires-Dist: ipython; extra == "dev"
Requires-Dist: mypy; extra == "dev"
Requires-Dist: pytest; extra == "dev"
Requires-Dist: ruff; extra == "dev"
Requires-Dist: sphinx; extra == "dev"
Requires-Dist: tox; extra == "dev"
Requires-Dist: twine; extra == "dev"
Dynamic: license-file
